flag_generation_assistant/__init__.py
flag_generation_assistant/config.yml
flag_generation_assistant/main.py
flag_generation_assistant/module/__init__.py
flag_generation_assistant/module/qsnctf_progress/__init__.py
flag_generation_assistant/module/qsnctf_welcome/__init__.py
flag_generation_assistant-0.1.4.dist-info/METADATA
flag_generation_assistant-0.1.4.dist-info/WHEEL
flag_generation_assistant-0.1.4.dist-info/entry_points.txt
flag_generation_assistant-0.1.4.dist-info/top_level.txt
flag_generation_assistant-0.1.4.dist-info/RECORD
