Metadata-Version: 2.4
Name: flag_generation_assistant
Version: 0.1.4
Summary: 青少年CTF Flag 生成工具
Author-email: Moxin <1044631097@qq.com>
License: MIT
Classifier: Programming Language :: Python :: 3
Classifier: License :: OSI Approved :: MIT License
Classifier: Operating System :: OS Independent
Requires-Python: >=3.8
Requires-Dist: pyyaml
Requires-Dist: rich
Requires-Dist: questionary
